tfseqrec/__init__.py
tfseqrec/loader.py
tfseqrec/losses.py
tfseqrec/metrics.py
tfseqrec/utils.py
tfseqrec/visualizer.py
tfseqrec-0.0.2.dist-info/METADATA
tfseqrec-0.0.2.dist-info/WHEEL
tfseqrec-0.0.2.dist-info/top_level.txt
tfseqrec-0.0.2.dist-info/RECORD
