Metadata-Version: 2.1
Name: tfseqrec
Version: 0.0.2
Summary: TensorFlow 2 toolkit for Sequence-level Text Recognition with modules that simplify the steps to process & visualize sequence data, along with common recognition loss functions & evaluation metrics
Home-page: https://github.com/18520339/tf2-sequence-recognition-toolkit
Author: Quan Dang
Author-email: 18520339@gm.uit.edu.vn
Classifier: Programming Language :: Python :: 3
Classifier: License :: OSI Approved :: MIT License
Classifier: Operating System :: OS Independent
